stash_graphql_client/UPDATE_GRAPHQL_SCHEMA.md
stash_graphql_client/__init__.py
stash_graphql_client/client/__init__.py
stash_graphql_client/client/base.py
stash_graphql_client/client/mixins/__init__.py
stash_graphql_client/client/mixins/config.py
stash_graphql_client/client/mixins/file.py
stash_graphql_client/client/mixins/filter.py
stash_graphql_client/client/mixins/gallery.py
stash_graphql_client/client/mixins/group.py
stash_graphql_client/client/mixins/image.py
stash_graphql_client/client/mixins/jobs.py
stash_graphql_client/client/mixins/marker.py
stash_graphql_client/client/mixins/metadata.py
stash_graphql_client/client/mixins/not_implemented.py
stash_graphql_client/client/mixins/package.py
stash_graphql_client/client/mixins/performer.py
stash_graphql_client/client/mixins/plugin.py
stash_graphql_client/client/mixins/protocols.py
stash_graphql_client/client/mixins/scene.py
stash_graphql_client/client/mixins/scraper.py
stash_graphql_client/client/mixins/studio.py
stash_graphql_client/client/mixins/subscription.py
stash_graphql_client/client/mixins/system_query.py
stash_graphql_client/client/mixins/tag.py
stash_graphql_client/client/mixins/version.py
stash_graphql_client/client/protocols.py
stash_graphql_client/client/utils.py
stash_graphql_client/client_helpers.py
stash_graphql_client/context.py
stash_graphql_client/errors.py
stash_graphql_client/fragments.py
stash_graphql_client/logging.py
stash_graphql_client/py.typed
stash_graphql_client/schema/schema.graphql
stash_graphql_client/schema/types/config.graphql
stash_graphql_client/schema/types/dlna.graphql
stash_graphql_client/schema/types/file.graphql
stash_graphql_client/schema/types/filters.graphql
stash_graphql_client/schema/types/gallery-chapter.graphql
stash_graphql_client/schema/types/gallery.graphql
stash_graphql_client/schema/types/group.graphql
stash_graphql_client/schema/types/image.graphql
stash_graphql_client/schema/types/job.graphql
stash_graphql_client/schema/types/logging.graphql
stash_graphql_client-0.10.10.dist-info/METADATA
stash_graphql_client-0.10.10.dist-info/WHEEL
stash_graphql_client-0.10.10.dist-info/licenses/LICENSE
stash_graphql_client-0.10.10.dist-info/RECORD
