Metadata-Version: 2.4
Name: stash-graphql-client
Version: 0.10.10
Summary: Async Python client for Stash GraphQL API
License: AGPL-3.0-or-later
License-File: LICENSE
Keywords: stash,stashapp,graphql,graphql-client,async,pydantic,metadata,media-management
Author: Jakan
Author-email: github@jakan.co
Requires-Python: >=3.12,<4.0
Classifier: Development Status :: 4 - Beta
Classifier: Intended Audience :: Developers
Classifier: License :: OSI Approved :: GNU Affero General Public License v3 or later (AGPLv3+)
Classifier: Programming Language :: Python :: 3
Classifier: Programming Language :: Python :: 3.12
Classifier: Programming Language :: Python :: 3.13
Classifier: Framework :: Pydantic
Classifier: Framework :: Pydantic :: 2
Classifier: Topic :: Software Development :: Libraries :: Python Modules
Classifier: Topic :: Multimedia :: Graphics
Classifier: Topic :: Database
Classifier: Typing :: Typed
Classifier: Operating System :: OS Independent
Requires-Dist: gql[httpx,websockets] (>=4.0.0)
Requires-Dist: httpx-retries (>=0.4.3)
Requires-Dist: httpx[http2] (>=0.28.1)
Requires-Dist: loguru (>=0.7.3,<0.8.0)
Requires-Dist: multidict (>=6.7.0)
Requires-Dist: pydantic (>=2.6.4)
Requires-Dist: pydantic-extra-types (>=2.10.6)
Requires-Dist: websocket-client (>=1.8.0)
Requires-Dist: websockets (>=15.0.0)
Project-URL: Changelog, https://github.com/Jakan-Kink/stash-graphql-client/blob/main/CHANGELOG.md
Project-URL: Documentation, https://jakan-kink.github.io/stash-graphql-client/
Project-URL: Homepage, https://github.com/Jakan-Kink/stash-graphql-client
Project-URL: Issues, https://github.com/Jakan-Kink/stash-graphql-client/issues
Project-URL: Repository, https://github.com/Jakan-Kink/stash-graphql-client
Project-URL: Stash GitHub, https://github.com/stashapp/stash
